odoo10_addon_sale_stock_variant_configurator-10.0.1.0.0-py2.7-nspkg.pth
odoo/addons/sale_stock_variant_configurator/README.rst
odoo/addons/sale_stock_variant_configurator/__init__.py
odoo/addons/sale_stock_variant_configurator/__manifest__.py
odoo/addons/sale_stock_variant_configurator/models/__init__.py
odoo/addons/sale_stock_variant_configurator/models/sale_order.py
odoo10_addon_sale_stock_variant_configurator-10.0.1.0.0.dist-info/DESCRIPTION.rst
odoo10_addon_sale_stock_variant_configurator-10.0.1.0.0.dist-info/METADATA
odoo10_addon_sale_stock_variant_configurator-10.0.1.0.0.dist-info/RECORD
odoo10_addon_sale_stock_variant_configurator-10.0.1.0.0.dist-info/WHEEL
odoo10_addon_sale_stock_variant_configurator-10.0.1.0.0.dist-info/metadata.json
odoo10_addon_sale_stock_variant_configurator-10.0.1.0.0.dist-info/namespace_packages.txt
odoo10_addon_sale_stock_variant_configurator-10.0.1.0.0.dist-info/top_level.txt
